setup.cfg
setup.py
codonOpt/SeqMake.py
codonOpt/__init__.py
codonOpt/global_vars.py
codonOpt.egg-info/PKG-INFO
codonOpt.egg-info/SOURCES.txt
codonOpt.egg-info/dependency_links.txt
codonOpt.egg-info/top_level.txt
codonOpt/AnalysisRedesignTools/GCTools.py
codonOpt/AnalysisRedesignTools/GeneralFunctions.py
codonOpt/AnalysisRedesignTools/MFE.py
codonOpt/AnalysisRedesignTools/MotifFinder.py
codonOpt/AnalysisRedesignTools/ViennaRNA_wrapper.py
codonOpt/AnalysisRedesignTools/__init__.py
codonOpt/test/__init__.py
codonOpt/test/tests_seqmake.py