Metadata-Version: 1.1
Name: codonOpt
Version: 0.22
Summary: A package for codon optimisation
Home-page: https://github.com/willfinnigan/codonOpt
Author: William Finnigan
Author-email: wjafinnigan@gmail.com
License: MIT
Download-URL: https://github.com/willfinnigan/codonOpt/archive/0.21.tar.gz
Keywords: DNA,Codon Optimisation,Gene Design
Platform: UNKNOWN
